{
    "id": "dbpedia_8361_2",
    "rank": 38,
    "data": {
        "url": "https://www.mid-day.com/news/opinion/article/lost-page-of-revolution-on-stage-22101187",
        "read_more_link": "",
        "language": "en",
        "title": "Lost page of revolution on stage",
        "top_image": "https://images.mid-day.com/images/images/2019/nov/anant-palshikar_l.jpg",
        "meta_img": "https://images.mid-day.com/images/images/2019/nov/anant-palshikar_l.jpg",
        "images": [
            "https://www.mid-day.com/assets/images/notification.gif",
            "https://www.mid-day.com/assets/images/webstories-icon.png",
            "https://www.mid-day.com/assets/images/youtube-shorts-icon.png",
            "https://www.mid-day.com/assets/images/logo.png",
            "https://www.mid-day.com/assets/images/webstories-icon.png",
            "https://www.mid-day.com/assets/images/youtube-shorts-icon.png"
        ],
        "movies": [],
        "keywords": [],
        "meta_keywords": [
            "RSS",
            "Jharkhand",
            "Birsa Munda Book",
            "Sunday midday"
        ],
        "tags": null,
        "authors": [
            "Sumedha Raikar Mhatre"
        ],
        "publish_date": "2019-11-17T05:30:00",
        "summary": "",
        "meta_description": "",
        "meta_lang": "en",
        "meta_favicon": "https://www.mid-day.com/md-48.ico",
        "meta_site_name": "Mid-day",
        "canonical_link": "https://www.mid-day.com/news/opinion/article/lost-page-of-revolution-on-stage-22101187",
        "text": "Web Stories\n\nShorts"
    }
}