{
    "id": "dbpedia_9196_3",
    "rank": 25,
    "data": {
        "url": "https://www.timeanddate.com/worldclock/%401270752",
        "read_more_link": "",
        "language": "en",
        "title": "Current Local Time in Gulbarga, Karnataka, India",
        "top_image": "https://www.timeanddate.com/scripts/cityog.php?title=Current%20Local%20Time%20in&city=Gulbarga&state=Karnataka&country=India",
        "meta_img": "https://www.timeanddate.com/scripts/cityog.php?title=Current%20Local%20Time%20in&city=Gulbarga&state=Karnataka&country=India",
        "images": [
            "https://c.tadst.com/gfx/n/logo/logo-2021--horizontal-inverted-darkbg.svg",
            "https://c.tadst.com/gfx/n/fl/48/in.png",
            "https://c.tadst.com/gfx/citymap/in-10.png?9",
            "https://c.tadst.com/gfx/n/icon/icon-map-pin.png",
            "https://c.tadst.com/gfx/w/svg/wt-6.svg",
            "https://c.tadst.com/gfx/w/svg/wt-22.svg",
            "https://c.tadst.com/gfx/w/svg/wt-21.svg",
            "https://c.tadst.com/gfx/n/i/wc-tmz.png",
            "https://c.tadst.com/gfx/n/i/wc-nodst.png",
            "https://c.tadst.com/gfx/n/i/wc-dff.png",
            "https://c.tadst.com/gfx/n/i/wc-snr.png",
            "https://c.tadst.com/gfx/n/i/wc-sns.png",
            "https://c.tadst.com/gfx/n/i/wc-dln.png",
            "https://www.timeanddate.com/scripts/moon.php?m=1&i=0.998&p=2.163&r=4.668",
            "https://c.tadst.com/gfx/n/i/wc-cal.png",
            "https://c.tadst.com/gfx/n/i/wc-nrb.png",
            "https://c.tadst.com/gfx/n/logo/logo-2021--horizontal-inverted-darkbg.svg",
            "https://c.tadst.com/gfx/n/fl/128/in.png",
            "https://c.tadst.com/gfx/n/i/service__supporter.svg",
            "https://c.tadst.com/gfx/n/logo/logo-2021--horizontal-color-whitebg.svg"
        ],
        "movies": [],
        "keywords": [],
        "meta_keywords": [
            ""
        ],
        "tags": null,
        "authors": [],
        "publish_date": null,
        "summary": "",
        "meta_description": "Current local time in India – Karnataka – Gulbarga. Get Gulbarga's weather and area codes, time zone and DST. Explore Gulbarga's sunrise and sunset, moonrise and moonset.",
        "meta_lang": "en",
        "meta_favicon": "//c.tadst.com/favicon-48x48.png",
        "meta_site_name": "",
        "canonical_link": null,
        "text": "06:38:39 IST\n\nDienstag, 20. August 2024\n\nFullscreen\n\nCountry: IndiaState: KarnatakaType: Populated PlaceLat/Long: 17°20'N / 76°50'ECurrency: Indian Rupee (INR)Languages: Kannada\n\nAlso known as: GBI, Gul'barga, Gulbarga, Gulburga\n\n°C\n\nWeather\n\n24 °C\n\nOvercast.\n\n31 / 24 °C\n\nMi 21.31 / 24 °CDo 22.29 / 24 °C\n\nWeather by CustomWeather, © 2024\n\nMore weather details\n\nTime Zone\n\nIST (India Standard Time)\n\nUTC/GMT +5:30 hours\n\nNo DST\n\nNo Daylight Saving Time in 2024\n\nDifference\n\n3:30 hours ahead of\n\nFrankfurt\n\nAbout IST — India Standard Time\n\nSet your location\n\nSunrise\n\n06:06\n\n↑ 77° East\n\nSunset\n\n18:44\n\n↑ 283° West\n\nDay length\n\n12 hours, 38 minutes\n\n-52s shorter\n\nMoon 99.8%\n\nSet – 06:26\n\nRise – 19:26\n\nMore Sun & Moon in Gulbarga\n\n+ Show More Twilight and Moon Phase Information\n\nSolar Noon\n\nSun in South: 12:25\n\nAltitude: 84,9°\n\nAstronomical\n\nTwilight\n\n04:51 – 05:18\n\n19:33 – 19:59\n\nNautical\n\nTwilight\n\n05:18 – 05:44\n\n19:07 – 19:33\n\nCivil\n\nTwilight\n\n05:44 – 06:06\n\n18:44 – 19:07\n\nPrevious\n\nMoon Phase\n\nFull Moon\n\n19. August 2024\n\n23:55\n\nNext\n\nMoon Phase\n\nThird Quarter\n\n26. August 2024\n\n14:55\n\nNeed some help?\n\nCalendar & Holidays\n\nCreate India calendar\n\nUpcoming Holidays\n\n26. Aug - Janmashtami\n\n7. Sep - Ganesh Chaturthi/Vinayaka Chaturthi\n\n15. Sep - Onam\n\nMore Holidays in India\n\nAirports\n\nBegumpet Airport, BPM\n\nAbout 174 km E of Gulbarga\n\nChatrapati Shivaji International Airport, BOM\n\nAbout 462 km WNW of Gulbarga"
    }
}