{
    "id": "yago_25575_2",
    "rank": 34,
    "data": {
        "url": "https://www.bustle.com/p/the-9-saddest-er-episodes-of-all-time-will-make-even-the-toughest-fans-sob-8429134",
        "read_more_link": "",
        "language": "en",
        "title": "The 9 Saddest 'ER' Episodes Of All Time Will Make Even The Toughest Fans Sob",
        "top_image": "https://imgix.bustle.com/uploads/image/2018/3/7/252ce316-0d78-4633-a6ed-08890580bb46-vlcsnap-2013-10-21-23h54m31s150.png?w=1200&h=630&fit=crop&crop=faces&fm=jpg",
        "meta_img": "https://imgix.bustle.com/uploads/image/2018/3/7/252ce316-0d78-4633-a6ed-08890580bb46-vlcsnap-2013-10-21-23h54m31s150.png?w=1200&h=630&fit=crop&crop=faces&fm=jpg",
        "images": [
            "https://imgix.bustle.com/uploads/image/2018/3/7/252ce316-0d78-4633-a6ed-08890580bb46-vlcsnap-2013-10-21-23h54m31s150.png?w=248&q=50&dpr=2",
            "https://imgix.bustle.com/uploads/image/2018/3/7/b901ea27-c05a-499b-b053-b22d68e1524a-loveslabourlost.jpg?w=414&h=233&fit=crop&crop=faces&q=50&dpr=2",
            "https://imgix.bustle.com/uploads/image/2018/3/7/d1d23faa-9d3f-43dc-a33a-b9047ce62576-lucyknight2kelliemartin.jpg?w=414&h=311&fit=crop&crop=faces&q=50&dpr=2",
            "https://imgix.bustle.com/uploads/image/2018/3/7/d2dd5ab8-da57-4f47-86c2-7df1d99cc33c-hqdefault.jpg?w=414&h=259&fit=crop&crop=faces&q=50&dpr=2",
            "https://imgix.bustle.com/uploads/image/2018/3/7/f3189e22-cdce-441c-92a0-a50fc27b1996-235821_original.jpg?w=414&h=302&fit=crop&crop=faces&q=50&dpr=2",
            "https://imgix.bustle.com/uploads/image/2018/3/7/7d2fd82d-99c3-40e2-a925-c99e5ea71a37-yelchin-er.jpg?w=414&h=233&fit=crop&crop=faces&q=50&dpr=2",
            "https://imgix.bustle.com/uploads/image/2018/3/7/c1b74127-0cc4-48b0-8051-d9204a6537d5-mv5bmtm3mzgynzm1ml5bml5banbnxkftztcwnza1nzm2oq_v1_.jpg?w=414&h=241&fit=crop&crop=faces&q=50&dpr=2",
            "https://imgix.bustle.com/uploads/image/2018/3/7/0fd76d85-a8d3-4718-a484-98d4e00715c2-hqdefault.jpg?w=414&h=311&fit=crop&crop=faces&q=50&dpr=2",
            "https://imgix.bustle.com/uploads/image/2018/3/7/fe320673-dd08-4c8d-8d7b-610ea127248a-er-1021-2.jpg?w=414&h=235&fit=crop&crop=faces&q=50&dpr=2",
            "https://imgix.bustle.com/uploads/image/2018/3/7/3d2281c9-d871-4c24-b48e-833c928f0288-hqdefault.jpg?w=414&h=311&fit=crop&crop=faces&q=50&dpr=2",
            "https://imgix.bustle.com/uploads/getty/2024/8/23/d7355b1d/los-angeles-california-august.jpg?w=159&h=110&fit=crop&crop=faces&q=50&dpr=2",
            "https://imgix.bustle.com/uploads/image/2024/8/22/f1d0339d/sidebyside_template001.jpeg?w=159&h=110&fit=crop&crop=faces&q=50&dpr=2",
            "https://imgix.bustle.com/uploads/image/2024/8/16/96bf7477/eip_unit_01327r.jpg?w=159&h=110&fit=crop&crop=focalpoint&q=50&fp-x=0.476&fp-y=0.3656&dpr=2",
            "https://imgix.bustle.com/uploads/image/2024/8/15/9f3d5fe6/eip_unit_00146r.jpg?w=159&h=110&fit=crop&crop=focalpoint&q=50&fp-x=0.5123&fp-y=0.2966&dpr=2",
            "https://pixel.quantserve.com/pixel/p-xPmcrFNGfHkBg.gif",
            "https://sb.scorecardresearch.comp?c1=2&c2=17519299&v=3.9.1&cj=1",
            "https://www.facebook.com/tr?id=1636673763227734&ev=PageView&noscript=1"
        ],
        "movies": [],
        "keywords": [],
        "meta_keywords": [
            ""
        ],
        "tags": null,
        "authors": [
            "Danielle Burgos"
        ],
        "publish_date": "2018-03-07T19:50:55+00:00",
        "summary": "",
        "meta_description": "The traumas, the dramas — for over 15 seasons, ER took us right into County Central Hospital's heart of chaos to follow the rollercoaster ride of a day in the emergency room. If you still can't get enough of the beloved show, get out your…",
        "meta_lang": "en",
        "meta_favicon": "/favicon.ico",
        "meta_site_name": "Bustle",
        "canonical_link": "https://www.bustle.com/p/the-9-saddest-er-episodes-of-all-time-will-make-even-the-toughest-fans-sob-8429134",
        "text": "The traumas, the dramas — for over 15 seasons, ER took us right into County Central Hospital's heart of chaos to follow the rollercoaster ride of a day in the emergency room. If you still can't get enough of the beloved show, get out your economy-sized box of tissues, because here are the saddest ER episodes of all time.\n\nThe genius of the show, aside from regularly using super long (and difficult) tracking shots to put audiences in the middle of the action, was establishing real emotion amid chaos. Setting a show in an emergency room may seem contradictory for writing juicy drama, but ER managed to pull at our heartstrings all the time with its emotional plotlines and moving character arcs. And even re-watching the episodes today (as you now can on Hulu), it's clear that the show still packs a serious punch. 15 years is a long time to produce new, compelling content week after week, but it's a testament to ER's impressive writers' room that they created so many heartbreaking storylines that turned all of us viewers into total mush every time we watched.\n\nSo, without further ado, let's revisit the saddest and most moving episodes ER ever aired."
    }
}